iv2_utils/__init__.py
iv2_utils/iv2.py
iv2_utils-0.3.4.dist-info/licenses/LICENSE
iv2_utils-0.3.4.dist-info/METADATA
iv2_utils-0.3.4.dist-info/WHEEL
iv2_utils-0.3.4.dist-info/top_level.txt
iv2_utils-0.3.4.dist-info/RECORD
