Metadata-Version: 2.4
Name: iv2_utils
Version: 0.3.4
Summary: InternVideo2 Testing Utils
Author-email: Qingyun Li <qingy2019@outlook.com>
Project-URL: Homepage, https://github.com/pypa/sampleproject
Project-URL: Issues, https://github.com/pypa/sampleproject/issues
Classifier: Programming Language :: Python :: 3
Classifier: License :: OSI Approved :: MIT License
Classifier: Operating System :: OS Independent
Requires-Python: >=3.8
License-File: LICENSE
Dynamic: license-file
